{"assets/avatar_pic.jpg":["assets/avatar_pic.jpg"],"assets/header-logo.png":["assets/header-logo.png"],"assets/header-logo.svg":["assets/header-logo.svg"],"assets/logo-bw.png":["assets/logo-bw.png"],"assets/logo-outline.png":["assets/logo-outline.png"],"assets/logo-wbg.png":["assets/logo-wbg.png"],"assets/logo-wbg.svg":["assets/logo-wbg.svg"],"assets/logo.png":["assets/logo.png"],"assets/logo.svg":["assets/logo.svg"],"assets/me.jpg":["assets/me.jpg"],"assets/nyan.gif":["assets/nyan.gif"],"assets/psu.jpg":["assets/psu.jpg"],"assets/pw-logo.png":["assets/pw-logo.png"],"assets/pw-logo.svg":["assets/pw-logo.svg"],"assets/sou.jpg":["assets/sou.jpg"],"packages/community_material_icon/fonts/materialdesignicons-webfont.ttf":["packages/community_material_icon/fonts/materialdesignicons-webfont.ttf"]}